fast_paseto-0.0.1.dist-info/METADATA
fast_paseto-0.0.1.dist-info/WHEEL
fast_paseto-0.0.1.dist-info/licenses/LICENSE
fast_paseto/__init__.py
fast_paseto/__init__.pyi
fast_paseto/fast_paseto.cp314-win_amd64.pyd
fast_paseto/py.typed
fast_paseto-0.0.1.dist-info/RECORD
