Metadata-Version: 2.4
Name: fast-paseto
Version: 0.0.1
Classifier: Programming Language :: Rust
Classifier: Programming Language :: Python :: Implementation :: CPython
Requires-Dist: hypothesis>=6.148.8
License-File: LICENSE
Summary: High-performance PASETO tokens implemented in Rust with Python bindings
Requires-Python: >=3.11
